color_tol/__init__.py
color_tol/funcs.py
color_tol/color_data/color_tol.json
color_tol-0.1.3.dist-info/DESCRIPTION.rst
color_tol-0.1.3.dist-info/METADATA
color_tol-0.1.3.dist-info/RECORD
color_tol-0.1.3.dist-info/WHEEL
color_tol-0.1.3.dist-info/metadata.json
color_tol-0.1.3.dist-info/top_level.txt
