Metadata-Version: 2.0
Name: color-tol
Version: 0.1.3
Summary: Optimized color schemes for data display
Home-page: https://github.com/lazarillo/color_tol
Author: Mike Williamson
Author-email: mwilliamson@pacific.edu
License: MIT
Keywords: visualization seaborn matplotib
Platform: UNKNOWN
Classifier: Development Status :: 2 - Pre-Alpha
Classifier: Programming Language :: Python :: 3.5
Classifier: License :: OSI Approved :: MIT License
Classifier: Intended Audience :: Science/Research
Classifier: Natural Language :: English
Classifier: Topic :: Scientific/Engineering :: Visualization
